webcoreframe/__init__.py
webcoreframe/application.cp39-win_amd64.pyd
webcoreframe/static.cp39-win_amd64.pyd
webcoreframe/view.cp39-win_amd64.pyd
webcoreframe/auth/__init__.py
webcoreframe/auth/helper.cp39-win_amd64.pyd
webcoreframe/decorators/__init__.py
webcoreframe/decorators/helper.cp39-win_amd64.pyd
webcoreframe/log/__init__.py
webcoreframe/log/helper.cp39-win_amd64.pyd
webcoreframe/middleware/__init__.py
webcoreframe/middleware/authentication.cp39-win_amd64.pyd
webcoreframe/middleware/authorization.cp39-win_amd64.pyd
webcoreframe/middleware/base.cp39-win_amd64.pyd
webcoreframe/middleware/performance_check.cp39-win_amd64.pyd
webcoreframe/middleware/system.cp39-win_amd64.pyd
webcoreframe/orm/__init__.py
webcoreframe/orm/helper.cp39-win_amd64.pyd
webcoreframe/plugins/__init__.py
webcoreframe/plugins/limiter_helper.cp39-win_amd64.pyd
webcoreframe/plugins/mail_helper.cp39-win_amd64.pyd
webcoreframe/plugins/plugins.cp39-win_amd64.pyd
webcoreframe/plugins/timer_helper.cp39-win_amd64.pyd
webcoreframe/plugins/license/__init__.py
webcoreframe/plugins/license/helper.cp39-win_amd64.pyd
webcoreframe/plugins/license/key.cp39-win_amd64.pyd
webcoreframe/plugins/license/view.cp39-win_amd64.pyd
webcoreframe/redis_helper/__init__.py
webcoreframe/redis_helper/helper.cp39-win_amd64.pyd
webcoreframe/utils/__init__.py
webcoreframe/utils/captcha.cp39-win_amd64.pyd
webcoreframe/utils/helper.cp39-win_amd64.pyd
webcoreframe/utils/fonts/fonts.ttf
webcoreframe-2023.9.5.post8.dist-info/METADATA
webcoreframe-2023.9.5.post8.dist-info/WHEEL
webcoreframe-2023.9.5.post8.dist-info/top_level.txt
webcoreframe-2023.9.5.post8.dist-info/RECORD
