Metadata-Version: 2.1
Name: webcoreframe
Version: 2023.9.5.post8
Summary: web develop core frame
Home-page: https://gitee.com/bean_jun/webcoreframe
Author: Bean-jun
Author-email: 1342104001@qq.com
License: MIT License
Platform: UNKNOWN
Classifier: License :: OSI Approved :: MIT License
Classifier: Programming Language :: Python :: 3.8
Classifier: Programming Language :: Python :: 3.9
Classifier: Programming Language :: Python :: 3.10
Requires-Dist: Flask >=2.3.2
Requires-Dist: Flask-RESTful >=0.3.9
Requires-Dist: Flask-SQLAlchemy >=3.0.5
Requires-Dist: pycryptodome >=3.17
Requires-Dist: redis >=4.5.4
Requires-Dist: APScheduler >=3.10.1
Requires-Dist: PyJWT >=2.6.0
Requires-Dist: Flask-Mail >=0.9.1
Requires-Dist: Flask-Limiter >=3.3.1
